{
  "apiVersion": "dashboard.grafana.app/v2",
  "kind": "Dashboard",
  "metadata": {
    "name": "4aBQsjSmz",
    "namespace": "default",
    "uid": "5fca75a8-8178-4a4f-8c65-c52c94d78b05",
    "resourceVersion": "1780194745962019",
    "generation": 22,
    "creationTimestamp": "2026-05-30T15:37:11Z",
    "labels": {
      "grafana.app/deprecatedInternalID": "2602328857993216"
    },
    "annotations": {
      "grafana.app/createdBy": "user:dfnmu1x7z1l34c",
      "grafana.app/folder": "",
      "grafana.app/saved-from-ui": "Grafana v13.1.0-25893932881 (fae43e29)",
      "grafana.app/updatedBy": "user:dfnmu1x7z1l34c",
      "grafana.app/updatedTimestamp": "2026-05-31T02:32:25Z"
    }
  },
  "spec": {
    "annotations": [
      {
        "kind": "AnnotationQuery",
        "spec": {
          "query": {
            "kind": "DataQuery",
            "group": "grafana",
            "version": "v0",
            "spec": {}
          },
          "enable": true,
          "hide": true,
          "iconColor": "rgba(0, 211, 255, 1)",
          "name": "Annotations & Alerts",
          "builtIn": true
        }
      }
    ],
    "cursorSync": "Off",
    "description": "Shows stats built from the Prometheus Nginx mtail log exporter rebuy-de/nginx-exporter or ndiazg/nginx-prometheus-exporter.",
    "editable": true,
    "elements": {
      "panel-10": {
        "kind": "Panel",
        "spec": {
          "id": 10,
          "title": "Status codes per second",
          "description": "",
          "links": [],
          "data": {
            "kind": "QueryGroup",
            "spec": {
              "queries": [
                {
                  "kind": "PanelQuery",
                  "spec": {
                    "query": {
                      "kind": "DataQuery",
                      "group": "prometheus",
                      "version": "v0",
                      "datasource": {
                        "name": "$datasource"
                      },
                      "spec": {
                        "editorMode": "code",
                        "expr": "sum(rate(http_requests_total{path=~\"$path\", status=~\"$status\"}[1m])) by (status)",
                        "format": "time_series",
                        "intervalFactor": 1,
                        "legendFormat": "{{code}}",
                        "range": true
                      }
                    },
                    "refId": "A",
                    "hidden": false
                  }
                }
              ],
              "transformations": [],
              "queryOptions": {}
            }
          },
          "vizConfig": {
            "kind": "VizConfig",
            "group": "timeseries",
            "version": "13.1.0-25893932881",
            "spec": {
              "options": {
                "annotations": {
                  "clustering": -1,
                  "multiLane": false
                },
                "legend": {
                  "calcs": [],
                  "displayMode": "list",
                  "placement": "bottom",
                  "showLegend": true
                },
                "tooltip": {
                  "hideZeros": false,
                  "mode": "multi",
                  "sort": "none"
                }
              },
              "fieldConfig": {
                "defaults": {
                  "unit": "short",
                  "thresholds": {
                    "mode": "absolute",
                    "steps": [
                      {
                        "value": 0,
                        "color": "green"
                      },
                      {
                        "value": 80,
                        "color": "red"
                      }
                    ]
                  },
                  "color": {
                    "mode": "palette-classic"
                  },
                  "custom": {
                    "axisBorderShow": false,
                    "axisCenteredZero": false,
                    "axisColorMode": "text",
                    "axisLabel": "",
                    "axisPlacement": "auto",
                    "barAlignment": 0,
                    "barWidthFactor": 0.6,
                    "drawStyle": "line",
                    "fillOpacity": 10,
                    "gradientMode": "none",
                    "hideFrom": {
                      "legend": false,
                      "tooltip": false,
                      "viz": false
                    },
                    "insertNulls": false,
                    "lineInterpolation": "linear",
                    "lineWidth": 1,
                    "pointSize": 5,
                    "scaleDistribution": {
                      "type": "linear"
                    },
                    "showPoints": "never",
                    "showValues": false,
                    "spanNulls": false,
                    "stacking": {
                      "group": "A",
                      "mode": "none"
                    },
                    "thresholdsStyle": {
                      "mode": "off"
                    }
                  }
                },
                "overrides": []
              }
            }
          }
        }
      },
      "panel-11": {
        "kind": "Panel",
        "spec": {
          "id": 11,
          "title": "p95 response time",
          "description": "",
          "links": [],
          "data": {
            "kind": "QueryGroup",
            "spec": {
              "queries": [
                {
                  "kind": "PanelQuery",
                  "spec": {
                    "query": {
                      "kind": "DataQuery",
                      "group": "prometheus",
                      "version": "v0",
                      "datasource": {
                        "name": "$datasource"
                      },
                      "spec": {
                        "editorMode": "code",
                        "expr": "histogram_quantile(\n  0.95,\n  sum by (le, path) (\n    rate(http_request_duration_seconds_bucket{path=~\"$path\"}[5m])\n  )\n)",
                        "legendFormat": "p95 Response Time",
                        "range": true
                      }
                    },
                    "refId": "A",
                    "hidden": false
                  }
                }
              ],
              "transformations": [],
              "queryOptions": {}
            }
          },
          "vizConfig": {
            "kind": "VizConfig",
            "group": "stat",
            "version": "13.1.0-25893932881",
            "spec": {
              "options": {
                "colorMode": "value",
                "graphMode": "area",
                "justifyMode": "center",
                "orientation": "auto",
                "percentChangeColorMode": "standard",
                "reduceOptions": {
                  "calcs": [
                    "lastNotNull"
                  ],
                  "fields": "",
                  "values": false
                },
                "showPercentChange": false,
                "textMode": "value_and_name",
                "wideLayout": true
              },
              "fieldConfig": {
                "defaults": {
                  "unit": "s",
                  "thresholds": {
                    "mode": "absolute",
                    "steps": [
                      {
                        "value": 0,
                        "color": "green"
                      },
                      {
                        "value": 0.2,
                        "color": "#EAB839"
                      },
                      {
                        "value": 0.5,
                        "color": "red"
                      }
                    ]
                  },
                  "color": {
                    "mode": "shades",
                    "fixedColor": "yellow"
                  }
                },
                "overrides": []
              }
            }
          }
        }
      },
      "panel-12": {
        "kind": "Panel",
        "spec": {
          "id": 12,
          "title": "Average Latency",
          "description": "",
          "links": [],
          "data": {
            "kind": "QueryGroup",
            "spec": {
              "queries": [
                {
                  "kind": "PanelQuery",
                  "spec": {
                    "query": {
                      "kind": "DataQuery",
                      "group": "prometheus",
                      "version": "v0",
                      "datasource": {
                        "name": "$datasource"
                      },
                      "spec": {
                        "editorMode": "code",
                        "expr": "sum(rate(http_request_duration_seconds_count{path=~\"$path\"}[5m]))",
                        "legendFormat": "Latency",
                        "range": true
                      }
                    },
                    "refId": "A",
                    "hidden": false
                  }
                }
              ],
              "transformations": [],
              "queryOptions": {}
            }
          },
          "vizConfig": {
            "kind": "VizConfig",
            "group": "stat",
            "version": "13.1.0-25893932881",
            "spec": {
              "options": {
                "colorMode": "value",
                "graphMode": "area",
                "justifyMode": "center",
                "orientation": "auto",
                "percentChangeColorMode": "same_as_value",
                "reduceOptions": {
                  "calcs": [
                    "lastNotNull"
                  ],
                  "fields": "",
                  "values": false
                },
                "showPercentChange": false,
                "text": {},
                "textMode": "value_and_name",
                "wideLayout": true
              },
              "fieldConfig": {
                "defaults": {
                  "unit": "ms",
                  "thresholds": {
                    "mode": "absolute",
                    "steps": [
                      {
                        "value": 0,
                        "color": "green"
                      },
                      {
                        "value": 80,
                        "color": "red"
                      }
                    ]
                  },
                  "color": {
                    "mode": "shades",
                    "fixedColor": "blue"
                  }
                },
                "overrides": []
              }
            }
          }
        }
      },
      "panel-13": {
        "kind": "Panel",
        "spec": {
          "id": 13,
          "title": "p99 response time",
          "description": "",
          "links": [],
          "data": {
            "kind": "QueryGroup",
            "spec": {
              "queries": [
                {
                  "kind": "PanelQuery",
                  "spec": {
                    "query": {
                      "kind": "DataQuery",
                      "group": "prometheus",
                      "version": "v0",
                      "datasource": {
                        "name": "$datasource"
                      },
                      "spec": {
                        "editorMode": "code",
                        "expr": "histogram_quantile(\n  0.99,\n  sum by (le) (\n    rate(http_request_duration_seconds_bucket{path=~\"$path\"}[5m])\n  )\n)",
                        "legendFormat": "p99 Response Time",
                        "range": true
                      }
                    },
                    "refId": "A",
                    "hidden": false
                  }
                }
              ],
              "transformations": [],
              "queryOptions": {}
            }
          },
          "vizConfig": {
            "kind": "VizConfig",
            "group": "stat",
            "version": "13.1.0-25893932881",
            "spec": {
              "options": {
                "colorMode": "value",
                "graphMode": "area",
                "justifyMode": "center",
                "orientation": "auto",
                "percentChangeColorMode": "standard",
                "reduceOptions": {
                  "calcs": [
                    "lastNotNull"
                  ],
                  "fields": "",
                  "values": false
                },
                "showPercentChange": false,
                "textMode": "value_and_name",
                "wideLayout": true
              },
              "fieldConfig": {
                "defaults": {
                  "unit": "s",
                  "thresholds": {
                    "mode": "absolute",
                    "steps": [
                      {
                        "value": 0,
                        "color": "green"
                      },
                      {
                        "value": 0.2,
                        "color": "#EAB839"
                      },
                      {
                        "value": 0.5,
                        "color": "red"
                      }
                    ]
                  },
                  "color": {
                    "mode": "shades",
                    "fixedColor": "yellow"
                  }
                },
                "overrides": []
              }
            }
          }
        }
      },
      "panel-14": {
        "kind": "Panel",
        "spec": {
          "id": 14,
          "title": "Status codes per second",
          "description": "",
          "links": [],
          "data": {
            "kind": "QueryGroup",
            "spec": {
              "queries": [
                {
                  "kind": "PanelQuery",
                  "spec": {
                    "query": {
                      "kind": "DataQuery",
                      "group": "prometheus",
                      "version": "v0",
                      "datasource": {
                        "name": "$datasource"
                      },
                      "spec": {
                        "editorMode": "code",
                        "expr": "sum(rate(http_requests_total{path=~\"$path\", status=~\"$status\"}[1m])) by (method)",
                        "format": "time_series",
                        "intervalFactor": 1,
                        "legendFormat": "{{code}}",
                        "range": true
                      }
                    },
                    "refId": "A",
                    "hidden": false
                  }
                }
              ],
              "transformations": [],
              "queryOptions": {}
            }
          },
          "vizConfig": {
            "kind": "VizConfig",
            "group": "timeseries",
            "version": "13.1.0-25893932881",
            "spec": {
              "options": {
                "annotations": {
                  "clustering": -1,
                  "multiLane": false
                },
                "legend": {
                  "calcs": [],
                  "displayMode": "list",
                  "placement": "bottom",
                  "showLegend": true
                },
                "tooltip": {
                  "hideZeros": false,
                  "mode": "multi",
                  "sort": "none"
                }
              },
              "fieldConfig": {
                "defaults": {
                  "unit": "short",
                  "thresholds": {
                    "mode": "absolute",
                    "steps": [
                      {
                        "value": 0,
                        "color": "green"
                      },
                      {
                        "value": 80,
                        "color": "red"
                      }
                    ]
                  },
                  "color": {
                    "mode": "palette-classic"
                  },
                  "custom": {
                    "axisBorderShow": false,
                    "axisCenteredZero": false,
                    "axisColorMode": "text",
                    "axisLabel": "",
                    "axisPlacement": "auto",
                    "barAlignment": 0,
                    "barWidthFactor": 0.6,
                    "drawStyle": "line",
                    "fillOpacity": 10,
                    "gradientMode": "none",
                    "hideFrom": {
                      "legend": false,
                      "tooltip": false,
                      "viz": false
                    },
                    "insertNulls": false,
                    "lineInterpolation": "linear",
                    "lineWidth": 1,
                    "pointSize": 5,
                    "scaleDistribution": {
                      "type": "linear"
                    },
                    "showPoints": "never",
                    "showValues": false,
                    "spanNulls": false,
                    "stacking": {
                      "group": "A",
                      "mode": "none"
                    },
                    "thresholdsStyle": {
                      "mode": "off"
                    }
                  }
                },
                "overrides": []
              }
            }
          }
        }
      },
      "panel-2": {
        "kind": "Panel",
        "spec": {
          "id": 2,
          "title": "Average Response Time",
          "description": "",
          "links": [],
          "data": {
            "kind": "QueryGroup",
            "spec": {
              "queries": [
                {
                  "kind": "PanelQuery",
                  "spec": {
                    "query": {
                      "kind": "DataQuery",
                      "group": "prometheus",
                      "version": "v0",
                      "datasource": {
                        "name": "$datasource"
                      },
                      "spec": {
                        "editorMode": "code",
                        "expr": "sum(rate(http_request_duration_seconds_sum{app=~\"$path\", status=~\"$status\"}[5m])) by (path)",
                        "format": "time_series",
                        "intervalFactor": 1,
                        "legendFormat": "__auto",
                        "range": true
                      }
                    },
                    "refId": "A",
                    "hidden": false
                  }
                }
              ],
              "transformations": [],
              "queryOptions": {}
            }
          },
          "vizConfig": {
            "kind": "VizConfig",
            "group": "timeseries",
            "version": "13.1.0-25893932881",
            "spec": {
              "options": {
                "annotations": {
                  "clustering": -1,
                  "multiLane": false
                },
                "legend": {
                  "calcs": [],
                  "displayMode": "list",
                  "placement": "bottom",
                  "showLegend": true
                },
                "tooltip": {
                  "hideZeros": false,
                  "mode": "multi",
                  "sort": "none"
                }
              },
              "fieldConfig": {
                "defaults": {
                  "unit": "ms",
                  "thresholds": {
                    "mode": "absolute",
                    "steps": [
                      {
                        "value": 0,
                        "color": "green"
                      },
                      {
                        "value": 80,
                        "color": "red"
                      }
                    ]
                  },
                  "color": {
                    "mode": "palette-classic"
                  },
                  "custom": {
                    "axisBorderShow": false,
                    "axisCenteredZero": false,
                    "axisColorMode": "text",
                    "axisLabel": "",
                    "axisPlacement": "auto",
                    "barAlignment": 0,
                    "barWidthFactor": 0.6,
                    "drawStyle": "line",
                    "fillOpacity": 10,
                    "gradientMode": "none",
                    "hideFrom": {
                      "legend": false,
                      "tooltip": false,
                      "viz": false
                    },
                    "insertNulls": false,
                    "lineInterpolation": "linear",
                    "lineWidth": 1,
                    "pointSize": 5,
                    "scaleDistribution": {
                      "type": "linear"
                    },
                    "showPoints": "never",
                    "showValues": false,
                    "spanNulls": false,
                    "stacking": {
                      "group": "A",
                      "mode": "none"
                    },
                    "thresholdsStyle": {
                      "mode": "off"
                    }
                  }
                },
                "overrides": [
                  {
                    "matcher": {
                      "id": "byValue",
                      "options": {
                        "op": "gte",
                        "reducer": "allIsZero",
                        "value": 0
                      }
                    },
                    "properties": [
                      {
                        "id": "custom.hideFrom",
                        "value": {
                          "legend": true,
                          "tooltip": true,
                          "viz": false
                        }
                      }
                    ]
                  },
                  {
                    "matcher": {
                      "id": "byValue",
                      "options": {
                        "op": "gte",
                        "reducer": "allIsZero",
                        "value": 0
                      }
                    },
                    "properties": [
                      {
                        "id": "custom.hideFrom",
                        "value": {
                          "legend": true,
                          "tooltip": true,
                          "viz": false
                        }
                      }
                    ]
                  },
                  {
                    "matcher": {
                      "id": "byValue",
                      "options": {
                        "op": "gte",
                        "reducer": "allIsZero",
                        "value": 0
                      }
                    },
                    "properties": [
                      {
                        "id": "custom.hideFrom",
                        "value": {
                          "legend": true,
                          "tooltip": true,
                          "viz": false
                        }
                      }
                    ]
                  }
                ]
              }
            }
          }
        }
      },
      "panel-4": {
        "kind": "Panel",
        "spec": {
          "id": 4,
          "title": "Requests per Second",
          "description": "",
          "links": [],
          "data": {
            "kind": "QueryGroup",
            "spec": {
              "queries": [
                {
                  "kind": "PanelQuery",
                  "spec": {
                    "query": {
                      "kind": "DataQuery",
                      "group": "prometheus",
                      "version": "v0",
                      "datasource": {
                        "name": "$datasource"
                      },
                      "spec": {
                        "editorMode": "code",
                        "expr": "sum(rate(http_request_duration_seconds_count{path=~\"$path\", status=~\"$status\"}[1m])) by (path)",
                        "format": "time_series",
                        "intervalFactor": 1,
                        "legendFormat": "__auto",
                        "range": true
                      }
                    },
                    "refId": "A",
                    "hidden": false
                  }
                }
              ],
              "transformations": [],
              "queryOptions": {}
            }
          },
          "vizConfig": {
            "kind": "VizConfig",
            "group": "timeseries",
            "version": "13.1.0-25893932881",
            "spec": {
              "options": {
                "annotations": {
                  "clustering": -1,
                  "multiLane": false
                },
                "legend": {
                  "calcs": [],
                  "displayMode": "list",
                  "placement": "bottom",
                  "showLegend": true
                },
                "tooltip": {
                  "hideZeros": false,
                  "mode": "multi",
                  "sort": "none"
                }
              },
              "fieldConfig": {
                "defaults": {
                  "unit": "short",
                  "thresholds": {
                    "mode": "absolute",
                    "steps": [
                      {
                        "value": 0,
                        "color": "green"
                      },
                      {
                        "value": 80,
                        "color": "red"
                      }
                    ]
                  },
                  "color": {
                    "mode": "palette-classic"
                  },
                  "custom": {
                    "axisBorderShow": false,
                    "axisCenteredZero": false,
                    "axisColorMode": "text",
                    "axisLabel": "",
                    "axisPlacement": "auto",
                    "barAlignment": 0,
                    "barWidthFactor": 0.6,
                    "drawStyle": "line",
                    "fillOpacity": 10,
                    "gradientMode": "none",
                    "hideFrom": {
                      "legend": false,
                      "tooltip": false,
                      "viz": false
                    },
                    "insertNulls": false,
                    "lineInterpolation": "linear",
                    "lineWidth": 1,
                    "pointSize": 5,
                    "scaleDistribution": {
                      "type": "linear"
                    },
                    "showPoints": "never",
                    "showValues": false,
                    "spanNulls": false,
                    "stacking": {
                      "group": "A",
                      "mode": "none"
                    },
                    "thresholdsStyle": {
                      "mode": "off"
                    }
                  }
                },
                "overrides": []
              }
            }
          }
        }
      }
    },
    "layout": {
      "kind": "GridLayout",
      "spec": {
        "items": [
          {
            "kind": "GridLayoutItem",
            "spec": {
              "x": 0,
              "y": 0,
              "width": 6,
              "height": 6,
              "element": {
                "kind": "ElementReference",
                "name": "panel-11"
              }
            }
          },
          {
            "kind": "GridLayoutItem",
            "spec": {
              "x": 6,
              "y": 0,
              "width": 6,
              "height": 6,
              "element": {
                "kind": "ElementReference",
                "name": "panel-13"
              }
            }
          },
          {
            "kind": "GridLayoutItem",
            "spec": {
              "x": 12,
              "y": 0,
              "width": 7,
              "height": 6,
              "element": {
                "kind": "ElementReference",
                "name": "panel-12"
              }
            }
          },
          {
            "kind": "GridLayoutItem",
            "spec": {
              "x": 0,
              "y": 6,
              "width": 9,
              "height": 7,
              "element": {
                "kind": "ElementReference",
                "name": "panel-2"
              }
            }
          },
          {
            "kind": "GridLayoutItem",
            "spec": {
              "x": 9,
              "y": 6,
              "width": 10,
              "height": 7,
              "element": {
                "kind": "ElementReference",
                "name": "panel-4"
              }
            }
          },
          {
            "kind": "GridLayoutItem",
            "spec": {
              "x": 0,
              "y": 13,
              "width": 9,
              "height": 7,
              "element": {
                "kind": "ElementReference",
                "name": "panel-10"
              }
            }
          },
          {
            "kind": "GridLayoutItem",
            "spec": {
              "x": 9,
              "y": 13,
              "width": 10,
              "height": 7,
              "element": {
                "kind": "ElementReference",
                "name": "panel-14"
              }
            }
          }
        ]
      }
    },
    "links": [],
    "liveNow": false,
    "preload": false,
    "tags": [
      "nginx",
      "http"
    ],
    "timeSettings": {
      "timezone": "browser",
      "from": "now-15m",
      "to": "now",
      "autoRefresh": "10s",
      "autoRefreshIntervals": [
        "5s",
        "10s",
        "30s",
        "1m",
        "5m",
        "15m",
        "30m",
        "1h",
        "2h",
        "1d"
      ],
      "hideTimepicker": false,
      "fiscalYearStartMonth": 0
    },
    "title": "HTTP Request Performance",
    "variables": [
      {
        "kind": "DatasourceVariable",
        "spec": {
          "name": "datasource",
          "pluginId": "prometheus",
          "refresh": "onDashboardLoad",
          "regex": "",
          "current": {
            "text": "Prometheus",
            "value": "Prometheus"
          },
          "options": [],
          "multi": false,
          "includeAll": false,
          "hide": "dontHide",
          "skipUrlSync": false,
          "allowCustomValue": true
        }
      },
      {
        "kind": "QueryVariable",
        "spec": {
          "name": "namespace",
          "current": {
            "text": "",
            "value": ""
          },
          "hide": "dontHide",
          "refresh": "onDashboardLoad",
          "skipUrlSync": false,
          "query": {
            "kind": "DataQuery",
            "group": "prometheus",
            "version": "v0",
            "datasource": {
              "name": "$datasource"
            },
            "spec": {
              "__legacyStringValue": "label_values(nginx_up, namespace)"
            }
          },
          "regex": "",
          "regexApplyTo": "value",
          "sort": "alphabeticalAsc",
          "options": [],
          "multi": false,
          "includeAll": true,
          "allValue": ".*",
          "allowCustomValue": true
        }
      },
      {
        "kind": "QueryVariable",
        "spec": {
          "name": "path",
          "current": {
            "text": "All",
            "value": "$__all"
          },
          "label": "path",
          "hide": "dontHide",
          "refresh": "onTimeRangeChanged",
          "skipUrlSync": false,
          "query": {
            "kind": "DataQuery",
            "group": "prometheus",
            "version": "v0",
            "datasource": {
              "name": "$datasource"
            },
            "spec": {
              "qryType": 1,
              "query": "label_values(http_requests_total,path)",
              "refId": "PrometheusVariableQueryEditor-VariableQuery"
            }
          },
          "regex": "",
          "regexApplyTo": "value",
          "sort": "alphabeticalAsc",
          "definition": "label_values(http_requests_total,path)",
          "options": [],
          "multi": true,
          "includeAll": true,
          "allValue": ".*",
          "allowCustomValue": true
        }
      },
      {
        "kind": "QueryVariable",
        "spec": {
          "name": "status",
          "current": {
            "text": "All",
            "value": "$__all"
          },
          "label": "status",
          "hide": "dontHide",
          "refresh": "onDashboardLoad",
          "skipUrlSync": false,
          "query": {
            "kind": "DataQuery",
            "group": "prometheus",
            "version": "v0",
            "datasource": {
              "name": "PBFA97CFB590B2093"
            },
            "spec": {
              "qryType": 1,
              "query": "label_values(http_requests_total,status)",
              "refId": "PrometheusVariableQueryEditor-VariableQuery"
            }
          },
          "regex": "",
          "regexApplyTo": "value",
          "sort": "disabled",
          "definition": "label_values(http_requests_total,status)",
          "options": [],
          "multi": true,
          "includeAll": true,
          "allowCustomValue": true
        }
      }
    ]
  }
}